django_bigquery_connector-0.1.3.dist-info/licenses/LICENSE
django_bq/__init__.py
django_bq/base.py
django_bq/client.py
django_bq/creation.py
django_bq/features.py
django_bq/introspection.py
django_bq/operations.py
django_bq/schema.py
django_bq/gis/__init__.py
django_bq/gis/base.py
django_bq/gis/client.py
django_bq/gis/creation.py
django_bq/gis/features.py
django_bq/gis/introspection.py
django_bq/gis/operations.py
django_bq/gis/schema.py
django_bigquery_connector-0.1.3.dist-info/METADATA
django_bigquery_connector-0.1.3.dist-info/WHEEL
django_bigquery_connector-0.1.3.dist-info/top_level.txt
django_bigquery_connector-0.1.3.dist-info/RECORD
