Metadata-Version: 2.4
Name: django-bigquery-connector
Version: 0.1.3
Summary: Django ORM connector for Google BigQuery
Home-page: https://github.com/ossown/django-bigquery-connector
Author: Sidhavratha Kumar
Author-email: your.email@example.com
Project-URL: Bug Tracker, https://github.com/ossown/django-bigquery-connector/issues
Project-URL: Documentation, https://github.com/ossown/django-bigquery-connector
Project-URL: Source Code, https://github.com/ossown/django-bigquery-connector
Keywords: django,bigquery,database,orm,connector
Classifier: Development Status :: 3 - Alpha
Classifier: Framework :: Django
Classifier: Framework :: Django :: 4.1
Classifier: Framework :: Django :: 4.2
Classifier: Intended Audience :: Developers
Classifier: License :: OSI Approved :: MIT License
Classifier: Operating System :: OS Independent
Classifier: Programming Language :: Python :: 3
Classifier: Programming Language :: Python :: 3.9
Classifier: Programming Language :: Python :: 3.10
Classifier: Programming Language :: Python :: 3.11
Classifier: Topic :: Database
Classifier: Topic :: Software Development :: Libraries :: Python Modules
Requires-Python: >=3.9
License-File: LICENSE
Requires-Dist: django>=4.1
Requires-Dist: google-cloud-bigquery>=2.0.0
Provides-Extra: dev
Requires-Dist: pytest>=6.0.0; extra == "dev"
Requires-Dist: pytest-django>=4.0.0; extra == "dev"
Requires-Dist: black; extra == "dev"
Requires-Dist: flake8; extra == "dev"
Requires-Dist: isort; extra == "dev"
Requires-Dist: wheel; extra == "dev"
Requires-Dist: twine; extra == "dev"
Dynamic: author
Dynamic: author-email
Dynamic: classifier
Dynamic: description
Dynamic: description-content-type
Dynamic: home-page
Dynamic: keywords
Dynamic: license-file
Dynamic: project-url
Dynamic: provides-extra
Dynamic: requires-dist
Dynamic: requires-python
Dynamic: summary
